yeti_iga/CMakeLists.txt
yeti_iga/DOF.cpython-310-x86_64-linux-gnu.so
yeti_iga/__init__.py
yeti_iga/embeddedmapping.f90
yeti_iga/igaparmetrization.f90
yeti_iga/massmtrx.cpython-310-x86_64-linux-gnu.so
yeti_iga/parameters.f90
yeti_iga/reconstructionSOL.cpython-310-x86_64-linux-gnu.so
yeti_iga/stiffmtrx_elemstorage.cpython-310-x86_64-linux-gnu.so
yeti_iga/tools.cpython-310-x86_64-linux-gnu.so
yeti_iga/utils.cpython-310-x86_64-linux-gnu.so
yeti_iga/coupling/CMakeLists.txt
yeti_iga/coupling/CPLINGMatrix_disp.f
yeti_iga/coupling/CPLINGMatrix_rot.f
yeti_iga/coupling/CPLINGMatrix_stiffStruct_disp.f
yeti_iga/coupling/CPLINGMatrix_stiffStruct_rot.f
yeti_iga/coupling/GPsInfoAtInterface.f
yeti_iga/coupling/UCPGDISPMATRIX.f
yeti_iga/coupling/UCPGROTMATRIX.f
yeti_iga/coupling/__init__.py
yeti_iga/coupling/build_cplgmatrix.f90
yeti_iga/coupling/build_cplgmatrixU5.f90
yeti_iga/coupling/build_cplgmatrixU5_wdatabase.f90
yeti_iga/coupling/build_dirichletBCmatrix.f
yeti_iga/coupling/cplg_U5_wEmbedded.f90
yeti_iga/coupling/cplgmatrix.cpython-310-x86_64-linux-gnu.so
yeti_iga/coupling/eval_coupling_gpts.f90
yeti_iga/coupling/evaluatelgrgefcts.f
yeti_iga/coupling/get_gaussphysical.f
yeti_iga/coupling/weakInterfaceInfos.f
yeti_iga/fitting/CMakeLists.txt
yeti_iga/fitting/__init__.py
yeti_iga/fitting/grevillePhysicalCoords.f
yeti_iga/fitting/interpolate.cpython-310-x86_64-linux-gnu.so
yeti_iga/fitting/interpolationMatrix.f
yeti_iga/iga_wq_mf/.gitignore
yeti_iga/iga_wq_mf/CMakeLists.txt
yeti_iga/iga_wq_mf/README.md
yeti_iga/iga_wq_mf/__init__.py
yeti_iga/iga_wq_mf/assembly.cpython-310-x86_64-linux-gnu.so
yeti_iga/iga_wq_mf/basis_weights.cpython-310-x86_64-linux-gnu.so
yeti_iga/iga_wq_mf/solver.cpython-310-x86_64-linux-gnu.so
yeti_iga/iga_wq_mf/ThermoMechaIGA/Assembly_Time.py
yeti_iga/iga_wq_mf/ThermoMechaIGA/Post_treatment.py
yeti_iga/iga_wq_mf/ThermoMechaIGA/Simulations.py
yeti_iga/iga_wq_mf/ThermoMechaIGA/__init__.py
yeti_iga-0.1.1.dist-info/METADATA
yeti_iga-0.1.1.dist-info/WHEEL
yeti_iga-0.1.1.dist-info/RECORD
yeti_iga-0.1.1.dist-info/licenses/LICENSE
