Metadata-Version: 2.2
Name: yeti-iga
Version: 0.1.1
Summary: Yeti is an IGA code
Author-Email: Arnaud Duval <arnaud.duval@cnrs.fr>
License:                    GNU LESSER GENERAL PUBLIC LICENSE
Classifier: Programming Language :: Python :: 3
Classifier: Programming Language :: Fortran
Classifier: License :: OSI Approved :: GNU Lesser General Public License v3 (LGPLv3)
Classifier: Operating System :: POSIX :: Linux
Classifier: Development Status :: 2 - Pre-Alpha
Classifier: Environment :: Console
Classifier: Intended Audience :: Science/Research
Classifier: Topic :: Scientific/Engineering
Project-URL: Homepage, https://lamcosplm.insa-lyon.fr/projects/yeti
Project-URL: Issues, https://lamcosplm.insa-lyon.fr/plugins/tracker/?tracker=626
Requires-Python: >=3.9
Requires-Dist: numpy>=2
Requires-Dist: scipy>=1.13
Requires-Dist: nlopt>=2
